{
    "update_time": "資料日期: 20260723 (更新於 2026-07-23 11:15:43)",
    "total_count": 28,
    "data": [
        {
            "StockID": "3231",
            "Name": "緯創            ",
            "Foreign_True_Long": 79016,
            "Trust_True_Long": 1307,
            "Dealer_True_Long": 2397
        },
        {
            "StockID": "2317",
            "Name": "鴻海            ",
            "Foreign_True_Long": 23754,
            "Trust_True_Long": 559,
            "Dealer_True_Long": 639
        },
        {
            "StockID": "2324",
            "Name": "仁寶            ",
            "Foreign_True_Long": 11036,
            "Trust_True_Long": 94,
            "Dealer_True_Long": 954
        },
        {
            "StockID": "2409",
            "Name": "友達            ",
            "Foreign_True_Long": 9800,
            "Trust_True_Long": 19,
            "Dealer_True_Long": 23
        },
        {
            "StockID": "2313",
            "Name": "華通            ",
            "Foreign_True_Long": 8440,
            "Trust_True_Long": 3,
            "Dealer_True_Long": 400
        },
        {
            "StockID": "2634",
            "Name": "漢翔            ",
            "Foreign_True_Long": 5049,
            "Trust_True_Long": 333,
            "Dealer_True_Long": 140
        },
        {
            "StockID": "3481",
            "Name": "群創            ",
            "Foreign_True_Long": 4853,
            "Trust_True_Long": 334,
            "Dealer_True_Long": 603
        },
        {
            "StockID": "00935",
            "Name": "野村臺灣新科技50",
            "Foreign_True_Long": 1616,
            "Trust_True_Long": 470,
            "Dealer_True_Long": 3271
        },
        {
            "StockID": "2455",
            "Name": "全新            ",
            "Foreign_True_Long": 1481,
            "Trust_True_Long": 362,
            "Dealer_True_Long": 261
        },
        {
            "StockID": "3017",
            "Name": "奇鋐            ",
            "Foreign_True_Long": 1382,
            "Trust_True_Long": 133,
            "Dealer_True_Long": 61
        },
        {
            "StockID": "3702",
            "Name": "大聯大          ",
            "Foreign_True_Long": 943,
            "Trust_True_Long": 2736,
            "Dealer_True_Long": 290
        },
        {
            "StockID": "1515",
            "Name": "力山            ",
            "Foreign_True_Long": 670,
            "Trust_True_Long": 79,
            "Dealer_True_Long": 1
        },
        {
            "StockID": "6226",
            "Name": "光鼎            ",
            "Foreign_True_Long": 613,
            "Trust_True_Long": 56,
            "Dealer_True_Long": 10
        },
        {
            "StockID": "2492",
            "Name": "華新科          ",
            "Foreign_True_Long": 543,
            "Trust_True_Long": 308,
            "Dealer_True_Long": 843
        },
        {
            "StockID": "8046",
            "Name": "南電            ",
            "Foreign_True_Long": 482,
            "Trust_True_Long": 667,
            "Dealer_True_Long": 52
        },
        {
            "StockID": "2027",
            "Name": "大成鋼          ",
            "Foreign_True_Long": 454,
            "Trust_True_Long": 18,
            "Dealer_True_Long": 96
        },
        {
            "StockID": "3665",
            "Name": "貿聯-KY         ",
            "Foreign_True_Long": 392,
            "Trust_True_Long": 1278,
            "Dealer_True_Long": 52
        },
        {
            "StockID": "6834",
            "Name": "天二科技        ",
            "Foreign_True_Long": 311,
            "Trust_True_Long": 32,
            "Dealer_True_Long": 0
        },
        {
            "StockID": "8454",
            "Name": "富邦媒          ",
            "Foreign_True_Long": 202,
            "Trust_True_Long": 33,
            "Dealer_True_Long": 3
        },
        {
            "StockID": "6155",
            "Name": "鈞寶            ",
            "Foreign_True_Long": 120,
            "Trust_True_Long": 37,
            "Dealer_True_Long": 3
        },
        {
            "StockID": "3550",
            "Name": "聯穎            ",
            "Foreign_True_Long": 58,
            "Trust_True_Long": 48,
            "Dealer_True_Long": 4
        },
        {
            "StockID": "6278",
            "Name": "台表科          ",
            "Foreign_True_Long": 56,
            "Trust_True_Long": 72,
            "Dealer_True_Long": 8
        },
        {
            "StockID": "2243",
            "Name": "宏旭-KY         ",
            "Foreign_True_Long": 47,
            "Trust_True_Long": 12,
            "Dealer_True_Long": 4
        },
        {
            "StockID": "2392",
            "Name": "正崴            ",
            "Foreign_True_Long": 43,
            "Trust_True_Long": 5,
            "Dealer_True_Long": 5
        },
        {
            "StockID": "5607",
            "Name": "遠雄港          ",
            "Foreign_True_Long": 18,
            "Trust_True_Long": 2,
            "Dealer_True_Long": 2
        },
        {
            "StockID": "5288",
            "Name": "豐祥-KY         ",
            "Foreign_True_Long": 7,
            "Trust_True_Long": 8,
            "Dealer_True_Long": 1
        },
        {
            "StockID": "2484",
            "Name": "希華            ",
            "Foreign_True_Long": 3,
            "Trust_True_Long": 79,
            "Dealer_True_Long": 1
        },
        {
            "StockID": "4764",
            "Name": "雙鍵            ",
            "Foreign_True_Long": 0,
            "Trust_True_Long": 650,
            "Dealer_True_Long": 5
        }
    ]
}